sct2df/__init__.py
sct2df/parse.py
sct2df-0.1.1.dist-info/licenses/LICENSE
sct2df-0.1.1.dist-info/METADATA
sct2df-0.1.1.dist-info/WHEEL
sct2df-0.1.1.dist-info/top_level.txt
sct2df-0.1.1.dist-info/RECORD
