Metadata-Version: 2.4
Name: sct2df
Version: 0.1.1
Summary: Python library for converting SCT Netlist text files to DataFrames
Maintainer-email: Ian Cleary <python@iancleary.me>
License-Expression: MIT
Requires-Python: >=3.13
License-File: LICENSE
Provides-Extra: full
Requires-Dist: pandas; extra == "full"
Provides-Extra: pandas
Requires-Dist: pandas; extra == "pandas"
Provides-Extra: polars
Requires-Dist: polars; extra == "polars"
Dynamic: license-file
